{
    "id": 1033,
    "name": "Stair Climber Intervals",
    "category": "cardio",
    "subcategory": null,
    "muscles_worked": {
        "primary": [
            "quadriceps",
            "glutes",
            "calves"
        ],
        "secondary": [
            "core"
        ]
    },
    "difficulty": "intermediate",
    "equipment": [
        "stair climber"
    ],
    "instructions": [
        {
            "step": 1,
            "description": "Stand tall and avoid leaning heavily on the rails."
        },
        {
            "step": 2,
            "description": "Warm up for 3\u20135 minutes at a moderate pace."
        },
        {
            "step": 3,
            "description": "Perform 1\u20132 minute hard efforts focusing on full foot contact."
        },
        {
            "step": 4,
            "description": "Recover for equal or slightly longer durations at easy pace."
        },
        {
            "step": 5,
            "description": "Keep knees tracking over toes and posture upright."
        },
        {
            "step": 6,
            "description": "Cool down 3\u20135 minutes at low intensity."
        }
    ],
    "metrics": {
        "reps": null,
        "sets": null,
        "duration": "6\u201310 rounds x 1\u20132 min hard / 1\u20132 min easy",
        "calories_burned_per_minute": null
    },
    "progressions": {
        "easier": [
            1031
        ],
        "harder": []
    },
    "video_urls": [
        "https://www.youtube.com/watch?v=0zPA7_0j2xQ",
        "https://www.youtube.com/watch?v=2Y2tVvZB7Mw"
    ],
    "thumbnail_urls": [
        "https://img.youtube.com/vi/0zPA7_0j2xQ/0.jpg",
        "https://img.youtube.com/vi/2Y2tVvZB7Mw/0.jpg"
    ],
    "metadata": {
        "created_by": "auto_generator",
        "review_status": "draft",
        "date_created": "2025-10-09",
        "last_updated": "2025-10-09",
        "last_edited_by": null,
        "edit_history": []
    },
    "_comments": {
        "exercise_info": "Low-impact intervals that build leg endurance and capacity.",
        "form_tips": [
            "Stand tall; avoid hunching."
        ],
        "modifications": [
            "Shorten intervals while learning technique."
        ],
        "safety_tips": [
            "Use rails only for balance, not support."
        ]
    }
}